setup.py
django_subscription.egg-info/PKG-INFO
django_subscription.egg-info/SOURCES.txt
django_subscription.egg-info/dependency_links.txt
django_subscription.egg-info/top_level.txt
subscription/__init__.py
subscription/backends.py
subscription/base.py
subscription/client.py
subscription/cluster.py
subscription/context_processors.py
subscription/emitter.py
subscription/models.py
subscription/piston_handlers.py
subscription/stream.py
subscription/urls.py
subscription/views.py
subscription/management/__init__.py
subscription/management/commands/__init__.py
subscription/management/commands/delete_empty_subscriptions.py
subscription/migrations/0002_remove_dupes.py
subscription/migrations/0003_auto__add_unique_subscription_user_content_type_object_id.py
subscription/migrations/0004_initial.py
subscription/migrations/0005_simpler_streams.py
subscription/migrations/0006_limit_to_200.py
subscription/migrations/__init__.py
subscription/templatetags/__init__.py
subscription/templatetags/subscription_tags.py