Metadata-Version: 1.0
Name: django-subscription
Version: 0.4
Summary: Managing subscriptions in Django
Home-page: http://github.com/yeago/django-subscription
Author: Steve Yeago
Author-email: yeago999@gmail.com
License: UNKNOWN
Platform: UNKNOWN
Classifier: Framework :: Django
Classifier: Intended Audience :: Developers
Classifier: Intended Audience :: System Administrators
Classifier: Operating System :: OS Independent
Classifier: Topic :: Software Development
